garpix_page/CHANGELOG.md
garpix_page/CONTRIBUTING.md
garpix_page/MANIFEST.in
garpix_page/README.md
garpix_page/README.rst
garpix_page/__init__.py
garpix_page/apps.py
garpix_page/codegenerator.py
garpix_page/constants.py
garpix_page/settings.py
garpix_page/setup.py
garpix_page/signals.py
garpix_page/urls.py
garpix_page/__pycache__/__init__.cpython-38.pyc
garpix_page/__pycache__/apps.cpython-38.pyc
garpix_page/__pycache__/settings.cpython-38.pyc
garpix_page/__pycache__/signals.cpython-38.pyc
garpix_page/__pycache__/urls.cpython-38.pyc
garpix_page/admin/__init__.py
garpix_page/admin/base_page.py
garpix_page/admin/forms.py
garpix_page/admin/__pycache__/__init__.cpython-38.pyc
garpix_page/admin/__pycache__/base_page.cpython-38.pyc
garpix_page/admin/__pycache__/forms.cpython-38.pyc
garpix_page/admin/__pycache__/subpage_url.cpython-38.pyc
garpix_page/admin/components/base_component.py
garpix_page/admin/components/grapes_js_html.py
garpix_page/admin/components/grepesjs_mixin.py
garpix_page/admin/components/__pycache__/base_component.cpython-38.pyc
garpix_page/admin/components/__pycache__/grapes_js_html.cpython-38.pyc
garpix_page/admin/components/__pycache__/grepesjs_mixin.cpython-38.pyc
garpix_page/admin/settings/__init__.py
garpix_page/admin/settings/seo_template.py
garpix_page/admin/settings/site_config.py
garpix_page/admin/settings/__pycache__/__init__.cpython-38.pyc
garpix_page/admin/settings/__pycache__/seo_template.cpython-38.pyc
garpix_page/admin/settings/__pycache__/site_config.cpython-38.pyc
garpix_page/cache/__init__.py
garpix_page/cache/decorators.py
garpix_page/cache/page.py
garpix_page/cache/__pycache__/__init__.cpython-38.pyc
garpix_page/cache/__pycache__/page.cpython-38.pyc
garpix_page/contexts/__init__.py
garpix_page/contexts/global_context.py
garpix_page/contexts/__pycache__/__init__.cpython-38.pyc
garpix_page/contexts/__pycache__/global_context.cpython-38.pyc
garpix_page/fields/__init__.py
garpix_page/fields/grapes_js_html.py
garpix_page-2.48.2.dist-info/METADATA
garpix_page-2.48.2.dist-info/WHEEL
garpix_page-2.48.2.dist-info/top_level.txt
garpix_page-2.48.2.dist-info/RECORD
