Metadata-Version: 2.1
Name: garpix-page
Version: 2.48.2
Home-page: https://github.com/garpixcms/garpix_page
Author: Garpix LTD
Author-email: info@garpix.com
License: MIT
Classifier: Development Status :: 4 - Beta
Classifier: Environment :: Web Environment
Classifier: Intended Audience :: Developers
Classifier: License :: OSI Approved :: MIT License
Classifier: Operating System :: OS Independent
Classifier: Programming Language :: Python
Classifier: Framework :: Django
Classifier: Programming Language :: Python :: 3.6
Classifier: Programming Language :: Python :: 3.7
Classifier: Programming Language :: Python :: 3.8
Requires-Dist: Django (>=1.11)
Requires-Dist: django-polymorphic-tree-for-garpix-page (>=2.1.1)
Requires-Dist: django-modeltranslation (>=0.16.2)
Requires-Dist: django-multiurl (>=1.4.0)
Requires-Dist: djangorestframework (>=3.12.4)
Requires-Dist: garpix-utils (>=1.8.0)
Requires-Dist: django-tabbed-admin (>=1.0.4)
Requires-Dist: model-bakery (>=1.4.0)
Requires-Dist: garpix-admin-lock (==1.2.0)
Requires-Dist: psycopg2-binary (>=2.9.3)
Requires-Dist: celery (>=5.2.7)
